{
  "success": 0.6666666666666666,
  "instruction_giver": {
    "id": "U7C"
  },
  "instruction_follower": {
    "id": "U12C"
  },
  "dialogue_duration": 174.73099999999977,
  "audio": {
    "ig": "U7C_0_house.wav",
    "if": "U12C_0_house.wav"
  },
  "turns": [
    {
      "speaker": "U12C",
      "start_time": 491.37,
      "end_time": 491.53,
      "utterance": "OKAY",
      "turn_index": 0,
      "topic": "describing picture",
      "overlap": [
        {
          "speaker_before": "U12C",
          "start_time": 491.43,
          "turn_index": 1,
          "speaker_after": "U7C",
          "end_time": 491.53
        }
      ]
    },
    {
      "speaker": "U7C",
      "start_time": 491.43,
      "end_time": 491.95,
      "utterance": "OKAY",
      "turn_index": 1,
      "topic": "describing picture"
    },
    {
      "speaker": "U7C",
      "start_time": 492.22,
      "end_time": 494.69,
      "utterance": "I HAVE <%aa> SIX CLOUDS",
      "turn_index": 2,
      "topic": "describing picture"
    },
    {
      "speaker": "U7C",
      "start_time": 495.09,
      "end_time": 500.22,
      "utterance": "<%aa> <TO THE> TO THE LEFT <%aa> THE LOWER CLOUD IS BLACK",
      "turn_index": 3,
      "topic": "describing picture",
      "overlap": [
        {
          "speaker_before": "U7C",
          "speaker_after": "U7C",
          "turn_index": 4,
          "start_time": 495.2,
          "end_time": 495.66
        }
      ]
    },
    {
      "speaker": "U12C",
      "start_time": 495.2,
      "end_time": 495.66,
      "utterance": "ME TOO",
      "turn_index": 4,
      "topic": "describing picture"
    },
    {
      "speaker": "U12C",
      "start_time": 501.35,
      "end_time": 505.78,
      "utterance": "<I> MY SIX CLOUDS ARE WHITE I HAVE THREE ON THE LEFT OF THE SUN AND THREE",
      "turn_index": 5,
      "topic": "describing picture"
    },
    {
      "speaker": "U12C",
      "start_time": 505.98,
      "end_time": 507.51,
      "utterance": "ON THE RIGHT OF THE SUN BUT",
      "turn_index": 6,
      "topic": "describing picture",
      "overlap": [
        {
          "speaker_before": "U12C",
          "start_time": 507.5,
          "turn_index": 7,
          "speaker_after": "U7C",
          "end_time": 507.51
        }
      ]
    },
    {
      "speaker": "U7C",
      "start_time": 507.5,
      "end_time": 511.55,
      "utterance": "OKAY LET'S CLICK IT TO <THE> THE LOWER ONE ON THE LEFT YEAH",
      "turn_index": 7,
      "topic": "finding difference",
      "overlap": [
        {
          "speaker_before": "U7C",
          "speaker_after": "U7C",
          "turn_index": 8,
          "start_time": 508.32,
          "end_time": 508.57
        },
        {
          "speaker_before": "U7C",
          "speaker_after": "U7C",
          "turn_index": 9,
          "start_time": 509.73,
          "end_time": 510.67
        }
      ]
    },
    {
      "speaker": "U12C",
      "start_time": 508.32,
      "end_time": 508.57,
      "utterance": "YEAH",
      "turn_index": 8,
      "topic": "finding difference"
    },
    {
      "speaker": "U12C",
      "start_time": 509.73,
      "end_time": 510.67,
      "utterance": "LEFT LOW",
      "turn_index": 9,
      "topic": "finding difference"
    },
    {
      "speaker": "U12C",
      "start_time": 511.48,
      "end_time": 512.0,
      "utterance": "PERFECT",
      "turn_index": 10,
      "topic": "finding difference"
    },
    {
      "speaker": "U7C",
      "start_time": 512.72,
      "end_time": 514.51,
      "utterance": "THE SUN IS ORANGE",
      "turn_index": 11,
      "topic": "finding difference",
      "overlap": [
        {
          "speaker_before": "U7C",
          "start_time": 514.44,
          "turn_index": 12,
          "speaker_after": "U12C",
          "end_time": 514.51
        }
      ]
    },
    {
      "speaker": "U12C",
      "start_time": 514.44,
      "end_time": 515.79,
      "utterance": "YEAH MINE IS ORANGE TOO",
      "turn_index": 12,
      "topic": "describing object"
    },
    {
      "speaker": "U7C",
      "start_time": 516.39,
      "end_time": 518.19,
      "utterance": "OKAY AND IT'S IN THE MIDDLE OF THE PICTURE",
      "turn_index": 13,
      "topic": "describing object"
    },
    {
      "speaker": "U12C",
      "start_time": 518.69,
      "end_time": 518.96,
      "utterance": "YEAH",
      "turn_index": 14,
      "topic": "describing picture"
    },
    {
      "speaker": "U7C",
      "start_time": 519.63,
      "end_time": 521.71,
      "utterance": "<<%aa> TO> I HAVE <%aa>",
      "turn_index": 15,
      "topic": "describing picture"
    },
    {
      "speaker": "U7C",
      "start_time": 522.17,
      "end_time": 523.39,
      "utterance": "FIVE STONES",
      "turn_index": 16,
      "topic": "describing picture"
    },
    {
      "speaker": "U7C",
      "start_time": 523.74,
      "end_time": 524.31,
      "utterance": "<%aa>",
      "turn_index": 17,
      "topic": "describing picture",
      "overlap": [
        {
          "speaker_before": "U7C",
          "start_time": 523.89,
          "turn_index": 18,
          "speaker_after": "U12C",
          "end_time": 524.31
        }
      ]
    },
    {
      "speaker": "U12C",
      "start_time": 523.89,
      "end_time": 524.59,
      "utterance": "I HAVE FOUR",
      "turn_index": 18,
      "topic": "describing picture"
    },
    {
      "speaker": "U7C",
      "start_time": 525.23,
      "end_time": 525.72,
      "utterance": "OKAY",
      "turn_index": 19,
      "topic": "describing picture",
      "overlap": [
        {
          "speaker_before": "U7C",
          "start_time": 525.33,
          "turn_index": 20,
          "speaker_after": "U12C",
          "end_time": 525.72
        }
      ]
    },
    {
      "speaker": "U12C",
      "start_time": 525.33,
      "end_time": 533.16,
      "utterance": "<TWO> TWO <%aa> BETWEEN THE BLUE AND THE GREEN LIKE BETWEEN THE SKY AND THE GRASS AND THE OTHER TWO JUST UNDERNEATH THE HOUSE",
      "turn_index": 20,
      "topic": "finding difference"
    },
    {
      "speaker": "U7C",
      "start_time": 533.89,
      "end_time": 535.69,
      "utterance": "OKAY SO <%aa> ON MY",
      "turn_index": 21,
      "topic": "finding difference"
    },
    {
      "speaker": "U7C",
      "start_time": 535.99,
      "end_time": 538.65,
      "utterance": "RIGHT <%aa> UNDERNEATH THE SKY I HAVE THREE",
      "turn_index": 22,
      "topic": "finding difference"
    },
    {
      "speaker": "U7C",
      "start_time": 539.26,
      "end_time": 540.16,
      "utterance": "<%aa>",
      "turn_index": 23,
      "topic": "finding difference"
    },
    {
      "speaker": "U7C",
      "start_time": 541.48,
      "end_time": 544.3,
      "utterance": "SO <LET'S> LET'S CLICK SOMEWHERE THERE",
      "turn_index": 24,
      "topic": "finding difference",
      "overlap": [
        {
          "speaker_before": "U7C",
          "start_time": 544.17,
          "turn_index": 25,
          "speaker_after": "U12C",
          "end_time": 544.3
        }
      ]
    },
    {
      "speaker": "U12C",
      "start_time": 544.17,
      "end_time": 544.54,
      "utterance": "YEAH",
      "turn_index": 25,
      "topic": "finding difference"
    },
    {
      "speaker": "U12C",
      "start_time": 544.79,
      "end_time": 547.29,
      "utterance": "IS THERE ONE ALMOST TOUCHING THE FLOWERS?",
      "turn_index": 26,
      "topic": "finding difference"
    },
    {
      "speaker": "U7C",
      "start_time": 547.9,
      "end_time": 549.3,
      "utterance": "(NO=)",
      "turn_index": 27,
      "topic": "finding difference",
      "overlap": [
        {
          "speaker_before": "U7C",
          "start_time": 548.88,
          "turn_index": 28,
          "speaker_after": "U12C",
          "end_time": 549.3
        }
      ]
    },
    {
      "speaker": "U12C",
      "start_time": 548.88,
      "end_time": 552.22,
      "utterance": "<OR> NO THERE'S LIKE TWO TOUCHING THE BLUE LINE",
      "turn_index": 28,
      "topic": "finding difference"
    },
    {
      "speaker": "U7C",
      "start_time": 552.47,
      "end_time": 553.1,
      "utterance": "YES",
      "turn_index": 29,
      "topic": "finding difference",
      "overlap": [
        {
          "speaker_before": "U7C",
          "start_time": 552.73,
          "turn_index": 30,
          "speaker_after": "U12C",
          "end_time": 553.1
        }
      ]
    },
    {
      "speaker": "U12C",
      "start_time": 552.73,
      "end_time": 554.8,
      "utterance": "MAYBE <OKAY> OKAY SO I CLICK THERE",
      "turn_index": 30,
      "topic": "finding difference"
    },
    {
      "speaker": "U7C",
      "start_time": 556.2,
      "end_time": 556.79,
      "utterance": "OKAY",
      "turn_index": 31,
      "topic": "finding difference"
    },
    {
      "speaker": "U7C",
      "start_time": 556.98,
      "end_time": 557.92,
      "utterance": "AND THE",
      "turn_index": 32,
      "topic": "describing picture",
      "overlap": [
        {
          "speaker_before": "U7C",
          "start_time": 557.13,
          "turn_index": 33,
          "speaker_after": "U12C",
          "end_time": 557.92
        }
      ]
    },
    {
      "speaker": "U12C",
      "start_time": 557.13,
      "end_time": 558.04,
      "utterance": "I HAVE TWO CATS",
      "turn_index": 33,
      "topic": "describing picture"
    },
    {
      "speaker": "U7C",
      "start_time": 558.71,
      "end_time": 560.45,
      "utterance": "TWO CATS YES THEY ARE GREY",
      "turn_index": 34,
      "topic": "describing picture"
    },
    {
      "speaker": "U12C",
      "start_time": 560.91,
      "end_time": 561.21,
      "utterance": "YEAH",
      "turn_index": 35,
      "topic": "describing object"
    },
    {
      "speaker": "U7C",
      "start_time": 561.79,
      "end_time": 564.47,
      "utterance": "AND THEY ARE ON WITHER SIDE OF THE HOUSE",
      "turn_index": 36,
      "topic": "describing object",
      "overlap": [
        {
          "speaker_before": "U7C",
          "start_time": 564.4,
          "turn_index": 37,
          "speaker_after": "U12C",
          "end_time": 564.47
        }
      ]
    },
    {
      "speaker": "U12C",
      "start_time": 564.4,
      "end_time": 565.35,
      "utterance": "YEAH EXACTLY",
      "turn_index": 37,
      "topic": "describing object"
    },
    {
      "speaker": "U7C",
      "start_time": 565.94,
      "end_time": 566.41,
      "utterance": "OKAY",
      "turn_index": 38,
      "topic": "describing object"
    },
    {
      "speaker": "U7C",
      "start_time": 566.77,
      "end_time": 570.28,
      "utterance": "<AND THEN <%aa>> ONE IN MY STONES ARE IN A DIFFERENT COLOR",
      "turn_index": 39,
      "topic": "describing object",
      "overlap": [
        {
          "speaker_before": "U7C",
          "speaker_after": "U7C",
          "turn_index": 40,
          "start_time": 567.27,
          "end_time": 568.61
        }
      ]
    },
    {
      "speaker": "U12C",
      "start_time": 567.27,
      "end_time": 568.61,
      "utterance": "WHAT ABOUTTHE FLOWERS",
      "turn_index": 40,
      "topic": "describing picture"
    },
    {
      "speaker": "U7C",
      "start_time": 570.57,
      "end_time": 574.37,
      "utterance": "<THE> THE LOWEST ONE TO THE RIGHT IS BLACK",
      "turn_index": 41,
      "topic": "describing picture",
      "overlap": [
        {
          "speaker_before": "U7C",
          "speaker_after": "U7C",
          "turn_index": 42,
          "start_time": 570.64,
          "end_time": 571.33
        }
      ]
    },
    {
      "speaker": "U12C",
      "start_time": 570.64,
      "end_time": 571.33,
      "utterance": "AH WHICH ONE",
      "turn_index": 42,
      "topic": "describing picture"
    },
    {
      "speaker": "U12C",
      "start_time": 574.47,
      "end_time": 574.88,
      "utterance": "OKAY",
      "turn_index": 43,
      "topic": "finding difference"
    },
    {
      "speaker": "U7C",
      "start_time": 575.48643928,
      "end_time": 576.16,
      "utterance": "LET'S CLICK THERE",
      "turn_index": 44,
      "topic": "finding difference",
      "overlap": [
        {
          "speaker_before": "U7C",
          "start_time": 575.54,
          "turn_index": 45,
          "speaker_after": "U12C",
          "end_time": 576.16
        }
      ]
    },
    {
      "speaker": "U12C",
      "start_time": 575.54,
      "end_time": 576.31,
      "utterance": "I'VE ALREADY GAVE",
      "turn_index": 45,
      "topic": "finding difference"
    },
    {
      "speaker": "U12C",
      "start_time": 576.6,
      "end_time": 576.83,
      "utterance": "YEAH",
      "turn_index": 46,
      "topic": "finding difference"
    },
    {
      "speaker": "U7C",
      "start_time": 577.12,
      "end_time": 579.79,
      "utterance": "<%aa> OKAY AND THEN THE HOUSE IS YELLOW",
      "turn_index": 47,
      "topic": "finding difference"
    },
    {
      "speaker": "U12C",
      "start_time": 580.08,
      "end_time": 580.37,
      "utterance": "YEAH",
      "turn_index": 48,
      "topic": "describing object"
    },
    {
      "speaker": "U7C",
      "start_time": 581.03,
      "end_time": 584.596540926,
      "utterance": "AND IT HAS GREY DOORS AND A GREY <%aa>",
      "turn_index": 49,
      "topic": "describing object"
    },
    {
      "speaker": "U7C",
      "start_time": 584.827475176,
      "end_time": 585.21,
      "utterance": "ROOF",
      "turn_index": 50,
      "topic": "describing object"
    },
    {
      "speaker": "U7C",
      "start_time": 585.91,
      "end_time": 589.95,
      "utterance": "AND <THREE <%aa>> THREE <%aa> WINDOWS",
      "turn_index": 51,
      "topic": "describing object",
      "overlap": [
        {
          "speaker_before": "U7C",
          "speaker_after": "U7C",
          "turn_index": 52,
          "start_time": 585.97,
          "end_time": 586.26
        }
      ]
    },
    {
      "speaker": "U12C",
      "start_time": 585.97,
      "end_time": 586.26,
      "utterance": "YEAH",
      "turn_index": 52,
      "topic": "describing object"
    },
    {
      "speaker": "U12C",
      "start_time": 589.76,
      "end_time": 591.52,
      "utterance": "WINDOWS <+ WHITE> ARE THEY WHITE?",
      "turn_index": 53,
      "topic": "describing object"
    },
    {
      "speaker": "U7C",
      "start_time": 591.71,
      "end_time": 592.28,
      "utterance": "YES",
      "turn_index": 54,
      "topic": "describing object"
    },
    {
      "speaker": "U12C",
      "start_time": 592.36,
      "end_time": 592.71,
      "utterance": "OKAY",
      "turn_index": 55,
      "topic": "describing object"
    },
    {
      "speaker": "U7C",
      "start_time": 593.63,
      "end_time": 595.92,
      "utterance": "AND I HAVE FIVE FLOWERS",
      "turn_index": 56,
      "topic": "describing object"
    },
    {
      "speaker": "U12C",
      "start_time": 596.12,
      "end_time": 596.91,
      "utterance": "I HAVE SIX",
      "turn_index": 57,
      "topic": "describing picture"
    },
    {
      "speaker": "U12C",
      "start_time": 597.09,
      "end_time": 598.63,
      "utterance": "THREE ON THE LEFT AND THREE ON THE RIGHT",
      "turn_index": 58,
      "topic": "describing picture",
      "overlap": [
        {
          "speaker_before": "U12C",
          "speaker_after": "U12C",
          "turn_index": 59,
          "start_time": 597.31,
          "end_time": 597.7
        }
      ]
    },
    {
      "speaker": "U7C",
      "start_time": 597.31,
      "end_time": 597.7,
      "utterance": "OKAY",
      "turn_index": 59,
      "topic": "describing picture"
    },
    {
      "speaker": "U7C",
      "start_time": 599.27,
      "end_time": 604.07,
      "utterance": "OKAY LET'S KICK <%aa> TO <THE> <THE LEFT> YOUR LEFT MOST",
      "turn_index": 60,
      "topic": "describing picture"
    },
    {
      "speaker": "U12C",
      "start_time": 604.32,
      "end_time": 604.75,
      "utterance": "OKAY",
      "turn_index": 61,
      "topic": "finding difference"
    },
    {
      "speaker": "U12C",
      "start_time": 605.02,
      "end_time": 608.08,
      "utterance": "<<I> I HAVE> THE FIRST ONE IS RED THEN BLUE THEN ORANGE",
      "turn_index": 62,
      "topic": "finding difference"
    },
    {
      "speaker": "U7C",
      "start_time": 608.71,
      "end_time": 609.06,
      "utterance": "YEAH",
      "turn_index": 63,
      "topic": "describing object"
    },
    {
      "speaker": "U7C",
      "start_time": 609.49,
      "end_time": 609.94,
      "utterance": "AND THEN?",
      "turn_index": 64,
      "topic": "describing object"
    },
    {
      "speaker": "U12C",
      "start_time": 610.27,
      "end_time": 614.38,
      "utterance": "<AND THEN> AND THE OTHER SET OF FLOWERS IT'S RED BLUE AND ORANGE",
      "turn_index": 65,
      "topic": "describing object"
    },
    {
      "speaker": "U7C",
      "start_time": 614.94,
      "end_time": 615.21,
      "utterance": "AH",
      "turn_index": 66,
      "topic": "describing object"
    },
    {
      "speaker": "U7C",
      "start_time": 615.44,
      "end_time": 616.25,
      "utterance": "OH I ACTUALLY",
      "turn_index": 67,
      "topic": "describing object"
    },
    {
      "speaker": "U7C",
      "start_time": 616.43,
      "end_time": 618.94,
      "utterance": "SUDDENLY CLICKED BUT I THINK WE ARE THE SAME",
      "turn_index": 68,
      "topic": "describing object"
    },
    {
      "speaker": "U12C",
      "start_time": 619.18,
      "end_time": 619.57,
      "utterance": "SO",
      "turn_index": 69,
      "topic": "describing object",
      "overlap": [
        {
          "speaker_before": "U12C",
          "start_time": 619.43,
          "turn_index": 70,
          "speaker_after": "U7C",
          "end_time": 619.57
        }
      ]
    },
    {
      "speaker": "U7C",
      "start_time": 619.43,
      "end_time": 621.0,
      "utterance": "<%aa> OKAY",
      "turn_index": 70,
      "topic": "describing object"
    },
    {
      "speaker": "U12C",
      "start_time": 621.06,
      "end_time": 623.84,
      "utterance": "SHALL I CLICK <ON THE LEFT RIGHT> ON THE LEFT SET OF FLOWERS",
      "turn_index": 71,
      "topic": "finding difference"
    },
    {
      "speaker": "U7C",
      "start_time": 624.31,
      "end_time": 625.01,
      "utterance": "(YES=)",
      "turn_index": 72,
      "topic": "finding difference"
    },
    {
      "speaker": "U7C",
      "start_time": 626.58,
      "end_time": 629.35,
      "utterance": "AND <%aa> THAT+S IT I THINK",
      "turn_index": 73,
      "topic": "finding difference"
    },
    {
      "speaker": "U12C",
      "start_time": 630.25,
      "end_time": 634.29,
      "utterance": "OKAY WHICH FLOWER DON'T YOU HAVE SORRY BECAUSE MAYBE THEY ARE VERY SPECIFIC",
      "turn_index": 74,
      "topic": "finding difference"
    },
    {
      "speaker": "U7C",
      "start_time": 634.68,
      "end_time": 639.02,
      "utterance": "YEAH <I HAVE <%aa>> I DON'T HAVE <%aa> THE RED ONE TO THE",
      "turn_index": 75,
      "topic": "finding difference"
    },
    {
      "speaker": "U7C",
      "start_time": 639.54,
      "end_time": 640.17,
      "utterance": "LEFT",
      "turn_index": 76,
      "topic": "finding difference",
      "overlap": [
        {
          "speaker_before": "U7C",
          "speaker_after": "U7C",
          "turn_index": 77,
          "start_time": 639.6,
          "end_time": 640.02
        }
      ]
    },
    {
      "speaker": "U12C",
      "start_time": 639.6,
      "end_time": 640.02,
      "utterance": "LEFT",
      "turn_index": 77,
      "topic": "finding difference"
    },
    {
      "speaker": "U12C",
      "start_time": 640.29,
      "end_time": 640.7,
      "utterance": "OKAY",
      "turn_index": 78,
      "topic": "finding difference"
    },
    {
      "speaker": "U12C",
      "start_time": 642.29,
      "end_time": 647.051870767,
      "utterance": "<%aa> AND THEN <THE> THE COLOR OF THE SUN AGAIN BECAUSE I'M NOT SURE IF IT'S LIKE YELLOW",
      "turn_index": 79,
      "topic": "finding difference"
    },
    {
      "speaker": "U12C",
      "start_time": 647.314780529,
      "end_time": 649.86,
      "utterance": "<IT'S> IT'S SIMILAR TO THE COLOR OF THE FLOWER",
      "turn_index": 80,
      "topic": "describing object"
    },
    {
      "speaker": "U7C",
      "start_time": 650.34,
      "end_time": 652.0,
      "utterance": "YEAH MINE TOO YEAH",
      "turn_index": 81,
      "topic": "describing object",
      "overlap": [
        {
          "speaker_before": "U7C",
          "speaker_after": "U7C",
          "turn_index": 82,
          "start_time": 650.41,
          "end_time": 650.85
        }
      ]
    },
    {
      "speaker": "U12C",
      "start_time": 650.41,
      "end_time": 650.85,
      "utterance": "BUT",
      "turn_index": 82,
      "topic": "describing object"
    },
    {
      "speaker": "U12C",
      "start_time": 652.25,
      "end_time": 653.76,
      "utterance": "BUT NOT EXACTLY THE SAME I DON'T KNOW",
      "turn_index": 83,
      "topic": "describing object"
    },
    {
      "speaker": "U7C",
      "start_time": 654.55,
      "end_time": 657.65,
      "utterance": "<%aa> (NO=) BUT <VERY> VERY SIMILAR",
      "turn_index": 84,
      "topic": "describing object",
      "overlap": [
        {
          "speaker_before": "U7C",
          "speaker_after": "U7C",
          "turn_index": 85,
          "start_time": 656.0,
          "end_time": 656.52
        }
      ]
    },
    {
      "speaker": "U12C",
      "start_time": 656.0,
      "end_time": 656.52,
      "utterance": "MINUTES",
      "turn_index": 85,
      "topic": "describing object"
    },
    {
      "speaker": "U12C",
      "start_time": 657.82,
      "end_time": 658.28,
      "utterance": "OKAY",
      "turn_index": 86,
      "topic": "describing object"
    },
    {
      "speaker": "U12C",
      "start_time": 658.5,
      "end_time": 661.34,
      "utterance": "<%aa> THEN I THINK WE SHOULDN'T CLICK I'M NOT SURE STILL ABOUT",
      "turn_index": 87,
      "topic": "describing object"
    },
    {
      "speaker": "U12C",
      "start_time": 661.73,
      "end_time": 661.95,
      "utterance": "BUT",
      "turn_index": 88,
      "topic": "describing object"
    },
    {
      "speaker": "U12C",
      "start_time": 662.33,
      "end_time": 663.66,
      "utterance": "YEAH OKAY LET'S TRY",
      "turn_index": 89,
      "topic": "end of differences",
      "overlap": [
        {
          "speaker_before": "U12C",
          "speaker_after": "U12C",
          "turn_index": 90,
          "start_time": 662.422302736,
          "end_time": 663.37
        }
      ]
    },
    {
      "speaker": "U7C",
      "start_time": 662.422302736,
      "end_time": 663.37,
      "utterance": "OKAY SHALL I CLICK",
      "turn_index": 90,
      "topic": "end of differences"
    }
  ]
}